[
  {
    "uid": "morning-dispatch-2026-04-07",
    "updateDate": "2026-04-07T12:02:06.341Z",
    "titleText": "The Dispatch - Morning Briefing",
    "mainText": "**Is Private Credit in Trouble?**\nIn recent weeks, major private credit investors on Wall Street, including BlackRock, Morgan Stanley, Apollo, Ares, and Blue Owl, have informed investors that they cannot access their funds. The market for private credit, which has expanded from $40 billion in 2000 to nearly $2 trillion today, is facing significant strain as numerous funds hit their redemption gates, limiting withdrawals to about five percent of fund assets each quarter.\n\nThis asset class, which involves lending outside the traditional banking system, has become increasingly appealing since the 2008 financial crisis, primarily because banks have been financially constrained from lending to riskier borrowers. However, with rising default rates and restrictions on liquidity, the attractiveness of private credit is diminishing. Increasingly, default rates are climbing, prompting comparisons to the 2008 financial crisis.\n\nAs investors rush to exit, many funds are being forced to restrict redemptions. While this was a standard practice due to the illiquid nature of private credit, the situation has been exacerbated by concerns over tech disruptions, particularly regarding the software industry. High exposure to artificial intelligence risks is causing fears of widespread defaults. Reports suggest that up to 35 percent of private credit could be exposed to potential disruptions caused by rapid AI changes, raising alarm bells.\n\nExperts, however, are not entirely convinced that the current situation poses a systemic risk to the broader financial system, citing that institutions are not as interlinked as they were leading up to the last crisis. Regulatory restrictions and increased scrutiny of private credit could create opportunities for better practices in the future. Meanwhile, the U.S. Department of Labor is proposing rule changes that would allow more individual investors into private credit, potentially inflating the current issues if those investors are unaware of the risks involved.\n\n**Artemis II Breaks Distance Record**\nThe Artemis II crew, consisting of NASA astronauts Victor Glover, Christina Koch, Reid Wiseman, and Canadian astronaut Jeremy Hansen, has set a new record by traveling farther from Earth than any humans before them. On Monday, the spacecraft passed about 4,100 miles past the moon, achieving a distance of 252,756 miles from Earth.\n\nThis distance exceeds the Apollo 13 mission by over 4,000 miles. The crew also experienced a pre-planned 40-minute blackout as they traveled around the back side of the moon, successfully regaining contact after the blackout. They had nearly seven hours to observe the moon during their pass, with some crew members capturing photos for their records. The crew is expected to land in the Pacific Ocean off the coast of San Diego on Friday evening.\n\n**Bannon Wins at Supreme Court**\nThe Supreme Court has issued a decision affecting Steve Bannon's legal case, sending it back to a lower court. This order could favor the Justice Department's request to dismiss the indictment against him. Bannon was convicted in July 2022 for contempt of Congress but maintains he acted on advice from his attorney. A prior federal appeals court decision had ruled that his actions were willful.\n\nThe decision comes after a request from Solicitor General D. John Sauer, suggesting that the government found that dismissing the case is in the interest of justice.\n\n**Board of Peace Gives Disarmament Agreement to Hamas**\nInternational peacekeeping organization the Board of Peace, led by President Donald Trump, is providing Hamas until the end of the week to reach a disarmament agreement. Meetings to discuss terms are scheduled to take place today in Cairo, Egypt. An internal document reveals that Israel would substantially withdraw its military presence from Gaza if the region is fully demilitarized.\n\nHamas has expressed oppositions to the disarmament, labeling it a continuation of genocide, while Israeli police arrested a suspected Hamas member related to a failed terrorist endeavor in the West Bank.\n\n**Iran Counters Ceasefire Proposal**\nNegotiations for a ceasefire involving the U.S., Iran, and other mediators have stalled, with Iran rejecting a 45-day ceasefire proposal in favor of a new 10-point plan aimed at achieving permanent peace. Iran demands guarantees against future attacks and ha",
    "redirectionUrl": "https://thedispatch.com"
  }
]